{
"meta":{"test_sets":[],"test_metrics":[],"learn_metrics":[{"best_value":"Min","name":"RMSE"}],"launch_mode":"Train","parameters":"","iteration_count":700,"learn_sets":["learn"],"name":"experiment"},
"iterations":[
{"learn":[0.9339719715],"iteration":0,"passed_time":0.4389803157,"remaining_time":306.8472407},
{"learn":[0.9285248651],"iteration":1,"passed_time":0.7752031953,"remaining_time":270.5459152},
{"learn":[0.9232090646],"iteration":2,"passed_time":1.085164906,"remaining_time":252.1199799},
{"learn":[0.9183746305],"iteration":3,"passed_time":1.36899372,"remaining_time":238.2049073},
{"learn":[0.9136324358],"iteration":4,"passed_time":1.656160823,"remaining_time":230.2063545},
{"learn":[0.9088945822],"iteration":5,"passed_time":1.933185279,"remaining_time":223.6050973},
{"learn":[0.9043491222],"iteration":6,"passed_time":2.225035945,"remaining_time":220.2785585},
{"learn":[0.8999768223],"iteration":7,"passed_time":2.526508956,"remaining_time":218.5430247},
{"learn":[0.8960075896],"iteration":8,"passed_time":2.835091602,"remaining_time":217.672033},
{"learn":[0.89232269],"iteration":9,"passed_time":3.131762341,"remaining_time":216.0916015},
{"learn":[0.8887229622],"iteration":10,"passed_time":3.449242469,"remaining_time":216.0480056},
{"learn":[0.8852786621],"iteration":11,"passed_time":3.726685454,"remaining_time":213.6632994},
{"learn":[0.8819406003],"iteration":12,"passed_time":4.013399092,"remaining_time":212.0927059},
{"learn":[0.8786552234],"iteration":13,"passed_time":4.313169347,"remaining_time":211.345298},
{"learn":[0.8754963033],"iteration":14,"passed_time":4.606810389,"remaining_time":210.3776744},
{"learn":[0.8725056301],"iteration":15,"passed_time":4.891300025,"remaining_time":209.1030761},
{"learn":[0.8698023691],"iteration":16,"passed_time":5.175786746,"remaining_time":207.944844},
{"learn":[0.8670157991],"iteration":17,"passed_time":5.474431497,"remaining_time":207.4201267},
{"learn":[0.8643458716],"iteration":18,"passed_time":5.763936137,"remaining_time":206.5916058},
{"learn":[0.8618837115],"iteration":19,"passed_time":6.048852534,"remaining_time":205.6609861},
{"learn":[0.8593547763],"iteration":20,"passed_time":6.346523989,"remaining_time":205.2042756},
{"learn":[0.8570289705],"iteration":21,"passed_time":6.616632167,"remaining_time":203.9125731},
{"learn":[0.8546388929],"iteration":22,"passed_time":6.897465769,"remaining_time":203.0254055},
{"learn":[0.8523018922],"iteration":23,"passed_time":7.188448455,"remaining_time":202.4746315},
{"learn":[0.8501294083],"iteration":24,"passed_time":7.466973854,"remaining_time":201.6082941},
{"learn":[0.8480085528],"iteration":25,"passed_time":7.764784578,"remaining_time":201.2871079},
{"learn":[0.846080059],"iteration":26,"passed_time":8.044351671,"remaining_time":200.5129139},
{"learn":[0.8441499365],"iteration":27,"passed_time":8.338973875,"remaining_time":200.135373},
{"learn":[0.8423068911],"iteration":28,"passed_time":8.645018905,"remaining_time":200.0278512},
{"learn":[0.8406068133],"iteration":29,"passed_time":8.935322081,"remaining_time":199.5555265},
{"learn":[0.8389823102],"iteration":30,"passed_time":9.218930938,"remaining_time":198.9504773},
{"learn":[0.8375127229],"iteration":31,"passed_time":9.502025165,"remaining_time":198.3547753},
{"learn":[0.8359956636],"iteration":32,"passed_time":9.774661744,"remaining_time":197.566648},
{"learn":[0.834417106],"iteration":33,"passed_time":10.05935602,"remaining_time":197.0450327},
{"learn":[0.8330309218],"iteration":34,"passed_time":10.3555869,"remaining_time":196.7561512},
{"learn":[0.8316106494],"iteration":35,"passed_time":10.63138387,"remaining_time":196.0899691},
{"learn":[0.8304232567],"iteration":36,"passed_time":10.94057464,"remaining_time":196.04327},
{"learn":[0.828914893],"iteration":37,"passed_time":11.25700797,"remaining_time":196.1089283},
{"learn":[0.8277342811],"iteration":38,"passed_time":11.54598696,"remaining_time":195.6896765},
{"learn":[0.8264625208],"iteration":39,"passed_time":11.85564402,"remaining_time":195.6181263},
{"learn":[0.8251033859],"iteration":40,"passed_time":12.16261264,"remaining_time":195.4917495},
{"learn":[0.8240700932],"iteration":41,"passed_time":12.43320524,"remaining_time":194.7868821},
{"learn":[0.8229991882],"iteration":42,"passed_time":12.71720739,"remaining_time":194.307099},
{"learn":[0.8219711395],"iteration":43,"passed_time":12.98947348,"remaining_time":193.661241},
{"learn":[0.8209718163],"iteration":44,"passed_time":13.24861712,"remaining_time":192.8409825},
{"learn":[0.8199033804],"iteration":45,"passed_time":13.51319222,"remaining_time":192.1223415},
{"learn":[0.8188718881],"iteration":46,"passed_time":13.7968233,"remaining_time":191.687779},
{"learn":[0.8178447791],"iteration":47,"passed_time":14.07755475,"remaining_time":191.2201187},
{"learn":[0.8170269638],"iteration":48,"passed_time":14.35720785,"remaining_time":190.7457614},
{"learn":[0.8160956152],"iteration":49,"passed_time":14.63350232,"remaining_time":190.2355302},
{"learn":[0.8152130214],"iteration":50,"passed_time":14.90929321,"remaining_time":189.7280646},
{"learn":[0.8142962364],"iteration":51,"passed_time":15.20621299,"remaining_time":189.492808},
{"learn":[0.8135445086],"iteration":52,"passed_time":15.48516707,"remaining_time":189.0359075},
{"learn":[0.8127588008],"iteration":53,"passed_time":15.75141,"remaining_time":188.4335344},
{"learn":[0.8117359249],"iteration":54,"passed_time":16.04317339,"remaining_time":188.1426697},
{"learn":[0.8109664588],"iteration":55,"passed_time":16.32779832,"remaining_time":187.7696807},
{"learn":[0.8101740644],"iteration":56,"passed_time":16.61506914,"remaining_time":187.4296396},
{"learn":[0.8094735767],"iteration":57,"passed_time":16.89507843,"remaining_time":187.0110406},
{"learn":[0.8086709759],"iteration":58,"passed_time":17.20039019,"remaining_time":186.8720358},
{"learn":[0.8079920033],"iteration":59,"passed_time":17.475209,"remaining_time":186.4022293},
{"learn":[0.8072739895],"iteration":60,"passed_time":17.75658046,"remaining_time":186.0074577},
{"learn":[0.8065095921],"iteration":61,"passed_time":18.02889671,"remaining_time":185.5231629},
{"learn":[0.8055772966],"iteration":62,"passed_time":18.33115835,"remaining_time":185.3483789},
{"learn":[0.8049282045],"iteration":63,"passed_time":18.60731956,"remaining_time":184.9102381},
{"learn":[0.8042921571],"iteration":64,"passed_time":18.89277487,"remaining_time":184.5678776},
{"learn":[0.8036902526],"iteration":65,"passed_time":19.16743891,"remaining_time":184.1235799},
{"learn":[0.8029808264],"iteration":66,"passed_time":19.46223588,"remaining_time":183.8745569},
{"learn":[0.8020361028],"iteration":67,"passed_time":19.7543674,"remaining_time":183.5994147},
{"learn":[0.8014647468],"iteration":68,"passed_time":20.02834216,"remaining_time":183.1577377},
{"learn":[0.8008537777],"iteration":69,"passed_time":20.29953084,"remaining_time":182.6957776},
{"learn":[0.8002190681],"iteration":70,"passed_time":20.57611203,"remaining_time":182.2869643},
{"learn":[0.7995691676],"iteration":71,"passed_time":20.86496803,"remaining_time":181.9888878},
{"learn":[0.7989958144],"iteration":72,"passed_time":21.15088557,"remaining_time":181.6658253},
{"learn":[0.7982118796],"iteration":73,"passed_time":21.44251532,"remaining_time":181.3920891},
{"learn":[0.797698072],"iteration":74,"passed_time":21.7178093,"remaining_time":180.9817442},
{"learn":[0.7972307085],"iteration":75,"passed_time":21.98971823,"remaining_time":180.5471602},
{"learn":[0.7968048036],"iteration":76,"passed_time":22.26243363,"remaining_time":180.1233266},
{"learn":[0.7962490938],"iteration":77,"passed_time":22.53416563,"remaining_time":179.6955259},
{"learn":[0.7957830999],"iteration":78,"passed_time":22.80509194,"remaining_time":179.2653429},
{"learn":[0.7952200474],"iteration":79,"passed_time":23.10076716,"remaining_time":179.0309455},
{"learn":[0.7946449842],"iteration":80,"passed_time":23.37849856,"remaining_time":178.6579088},
{"learn":[0.7942756724],"iteration":81,"passed_time":23.64674416,"remaining_time":178.215706},
{"learn":[0.7936299934],"iteration":82,"passed_time":23.93906376,"remaining_time":177.9566547},
{"learn":[0.793195693],"iteration":83,"passed_time":24.2162538,"remaining_time":177.5858612},
{"learn":[0.7925762461],"iteration":84,"passed_time":24.48623095,"remaining_time":177.1650828},
{"learn":[0.7921455685],"iteration":85,"passed_time":24.77251157,"remaining_time":176.8642105},
{"learn":[0.7917549047],"iteration":86,"passed_time":25.05903615,"remaining_time":176.5653927},
{"learn":[0.7910454123],"iteration":87,"passed_time":25.36884689,"remaining_time":176.4287988},
{"learn":[0.7905022311],"iteration":88,"passed_time":25.64640116,"remaining_time":176.0668664},
{"learn":[0.7900847423],"iteration":89,"passed_time":25.91626783,"remaining_time":175.6547042},
{"learn":[0.7896523134],"iteration":90,"passed_time":26.18080288,"remaining_time":175.2099885},
{"learn":[0.7891692318],"iteration":91,"passed_time":26.4629511,"remaining_time":174.8855899},
{"learn":[0.788743259],"iteration":92,"passed_time":26.74345661,"remaining_time":174.5513781},
{"learn":[0.7882473029],"iteration":93,"passed_time":27.04814084,"remaining_time":174.3741846},
{"learn":[0.7878668189],"iteration":94,"passed_time":27.43287194,"remaining_time":174.7040792},
{"learn":[0.7874131973],"iteration":95,"passed_time":27.71946467,"remaining_time":174.4016319},
{"learn":[0.7869459137],"iteration":96,"passed_time":28.00609164,"remaining_time":174.0997243},
{"learn":[0.7864807685],"iteration":97,"passed_time":28.31751619,"remaining_time":173.9504566},
{"learn":[0.7860812131],"iteration":98,"passed_time":28.60213716,"remaining_time":173.6351963},
{"learn":[0.7856432253],"iteration":99,"passed_time":28.8689485,"remaining_time":173.213691},
{"learn":[0.785129572],"iteration":100,"passed_time":29.15507094,"remaining_time":172.9097771},
{"learn":[0.7847660207],"iteration":101,"passed_time":29.42722696,"remaining_time":172.5243306},
{"learn":[0.7843542183],"iteration":102,"passed_time":29.69352331,"remaining_time":172.1071205},
{"learn":[0.7839126401],"iteration":103,"passed_time":29.978317,"remaining_time":171.7988166},
{"learn":[0.7835807429],"iteration":104,"passed_time":30.24732125,"remaining_time":171.4014871},
{"learn":[0.783213552],"iteration":105,"passed_time":30.53667488,"remaining_time":171.1206121},
{"learn":[0.7828843482],"iteration":106,"passed_time":30.80885946,"remaining_time":170.7444267},
{"learn":[0.7825365881],"iteration":107,"passed_time":31.08568786,"remaining_time":170.3956224},
{"learn":[0.7821498282],"iteration":108,"passed_time":31.38230032,"remaining_time":170.1554082},
{"learn":[0.7816213206],"iteration":109,"passed_time":31.67045354,"remaining_time":169.8687962},
{"learn":[0.7813795939],"iteration":110,"passed_time":31.93452036,"remaining_time":169.4543468},
{"learn":[0.7810941335],"iteration":111,"passed_time":32.21149498,"remaining_time":169.1103487},
{"learn":[0.7808278558],"iteration":112,"passed_time":32.47413266,"remaining_time":168.6930608},
{"learn":[0.7805037897],"iteration":113,"passed_time":32.7517834,"remaining_time":168.3556585},
{"learn":[0.7801660474],"iteration":114,"passed_time":33.05786071,"remaining_time":168.1639001},
{"learn":[0.7798635163],"iteration":115,"passed_time":33.3322798,"remaining_time":167.8107879},
{"learn":[0.7795560742],"iteration":116,"passed_time":33.58480834,"remaining_time":167.3499424},
{"learn":[0.7792486673],"iteration":117,"passed_time":33.87111867,"remaining_time":167.0592463},
{"learn":[0.778894193],"iteration":118,"passed_time":34.14366929,"remaining_time":166.7014442},
{"learn":[0.7785643577],"iteration":119,"passed_time":34.41879543,"remaining_time":166.3575113},
{"learn":[0.7781689121],"iteration":120,"passed_time":34.69236207,"remaining_time":166.0072532},
{"learn":[0.7779356188],"iteration":121,"passed_time":34.95785506,"remaining_time":165.6200018},
{"learn":[0.7776502564],"iteration":122,"passed_time":35.22200475,"remaining_time":165.2284288},
{"learn":[0.7771715168],"iteration":123,"passed_time":35.51623902,"remaining_time":164.9786587},
{"learn":[0.7768664575],"iteration":124,"passed_time":35.78605492,"remaining_time":164.6158526},
{"learn":[0.7766236386],"iteration":125,"passed_time":36.04898236,"remaining_time":164.2231418},
{"learn":[0.7763861106],"iteration":126,"passed_time":36.3269286,"remaining_time":163.9002369},
{"learn":[0.7760138436],"iteration":127,"passed_time":36.61267378,"remaining_time":163.6128859},
{"learn":[0.7757620442],"iteration":128,"passed_time":36.88408668,"remaining_time":163.2621201},
{"learn":[0.7754920093],"iteration":129,"passed_time":37.1565227,"remaining_time":162.9170611},
{"learn":[0.7751755847],"iteration":130,"passed_time":37.42213817,"remaining_time":162.5434856},
{"learn":[0.7748790886],"iteration":131,"passed_time":37.68492948,"remaining_time":162.1593935},
{"learn":[0.7746402308],"iteration":132,"passed_time":37.95362486,"remaining_time":161.8022954},
{"learn":[0.774433083],"iteration":133,"passed_time":38.22461413,"remaining_time":161.456206},
{"learn":[0.7740916633],"iteration":134,"passed_time":38.50710131,"remaining_time":161.1593499},
{"learn":[0.7737906788],"iteration":135,"passed_time":38.76993841,"remaining_time":160.7812152},
{"learn":[0.7735831043],"iteration":136,"passed_time":39.03665027,"remaining_time":160.4206869},
{"learn":[0.773293592],"iteration":137,"passed_time":39.30957844,"remaining_time":160.0868339},
{"learn":[0.7729133301],"iteration":138,"passed_time":39.58735547,"remaining_time":159.7734275},
{"learn":[0.7726511599],"iteration":139,"passed_time":39.85501974,"remaining_time":159.4200789},
{"learn":[0.7723946447],"iteration":140,"passed_time":40.1314162,"remaining_time":159.102565},
{"learn":[0.7720279812],"iteration":141,"passed_time":40.41271941,"remaining_time":158.8049115},
{"learn":[0.7717797189],"iteration":142,"passed_time":40.68870574,"remaining_time":158.4867769},
{"learn":[0.7715414825],"iteration":143,"passed_time":40.95714934,"remaining_time":158.1401044},
{"learn":[0.7713116785],"iteration":144,"passed_time":41.22059395,"remaining_time":157.7753769},
{"learn":[0.7710534021],"iteration":145,"passed_time":41.49330428,"remaining_time":157.4471957},
{"learn":[0.770767198],"iteration":146,"passed_time":41.76339434,"remaining_time":157.1099121},
{"learn":[0.7704261623],"iteration":147,"passed_time":42.04145923,"remaining_time":156.8032804},
{"learn":[0.7701788656],"iteration":148,"passed_time":42.29533578,"remaining_time":156.407584},
{"learn":[0.7698950101],"iteration":149,"passed_time":42.57143198,"remaining_time":156.0952506},
{"learn":[0.7696509932],"iteration":150,"passed_time":42.82736884,"remaining_time":155.7101026},
{"learn":[0.7693472034],"iteration":151,"passed_time":43.087344,"remaining_time":155.3412139},
{"learn":[0.7691337528],"iteration":152,"passed_time":43.35987757,"remaining_time":155.0186472},
{"learn":[0.7688710845],"iteration":153,"passed_time":43.63210145,"remaining_time":154.6956324},
{"learn":[0.7686937295],"iteration":154,"passed_time":43.89556142,"remaining_time":154.3424579},
{"learn":[0.7682694345],"iteration":155,"passed_time":44.18377498,"remaining_time":154.0767538},
{"learn":[0.7680436299],"iteration":156,"passed_time":44.45898192,"remaining_time":153.7657782},
{"learn":[0.7676985261],"iteration":157,"passed_time":44.73316446,"remaining_time":153.4517414},
{"learn":[0.7673618],"iteration":158,"passed_time":44.99716653,"remaining_time":153.1035666},
{"learn":[0.7671242856],"iteration":159,"passed_time":45.26791521,"remaining_time":152.7792138},
{"learn":[0.7668906164],"iteration":160,"passed_time":45.54091118,"remaining_time":152.4630505},
{"learn":[0.7666759824],"iteration":161,"passed_time":45.80449003,"remaining_time":152.1161459},
{"learn":[0.7664121209],"iteration":162,"passed_time":46.08264979,"remaining_time":151.8183002},
{"learn":[0.7660142057],"iteration":163,"passed_time":46.39204773,"remaining_time":151.6227901},
{"learn":[0.7656923266],"iteration":164,"passed_time":46.67146243,"remaining_time":151.3286812},
{"learn":[0.7653370126],"iteration":165,"passed_time":46.94806802,"remaining_time":151.0257128},
{"learn":[0.765110329],"iteration":166,"passed_time":47.22597478,"remaining_time":150.7272129},
{"learn":[0.7648530622],"iteration":167,"passed_time":47.49835735,"remaining_time":150.4114649},
{"learn":[0.7644952999],"iteration":168,"passed_time":47.78184767,"remaining_time":150.1311308},
{"learn":[0.7643073276],"iteration":169,"passed_time":48.04915847,"remaining_time":149.8003176},
{"learn":[0.7641349878],"iteration":170,"passed_time":48.31528949,"remaining_time":149.4665973},
{"learn":[0.7639438618],"iteration":171,"passed_time":48.60817935,"remaining_time":149.2158064},
{"learn":[0.763663457],"iteration":172,"passed_time":48.90741823,"remaining_time":148.9838694},
{"learn":[0.7634012996],"iteration":173,"passed_time":49.19366248,"remaining_time":148.7118762},
{"learn":[0.76318753],"iteration":174,"passed_time":49.47151348,"remaining_time":148.4145405},
{"learn":[0.7629189287],"iteration":175,"passed_time":49.75675401,"remaining_time":148.1394267},
{"learn":[0.7627265121],"iteration":176,"passed_time":50.02507971,"remaining_time":147.8142186},
{"learn":[0.7625219628],"iteration":177,"passed_time":50.30238046,"remaining_time":147.5159697},
{"learn":[0.762319644],"iteration":178,"passed_time":50.56828072,"remaining_time":147.1847724},
{"learn":[0.7621838896],"iteration":179,"passed_time":50.8257693,"remaining_time":146.8300002},
{"learn":[0.762028477],"iteration":180,"passed_time":51.09967582,"remaining_time":146.5233798},
{"learn":[0.7617607938],"iteration":181,"passed_time":51.3967086,"remaining_time":146.2829399},
{"learn":[0.761563711],"iteration":182,"passed_time":51.67530926,"remaining_time":145.9898081},
{"learn":[0.7613112625],"iteration":183,"passed_time":51.94608441,"remaining_time":145.6748889},
{"learn":[0.7611241074],"iteration":184,"passed_time":52.22359991,"remaining_time":145.3792106},
{"learn":[0.7608799112],"iteration":185,"passed_time":52.4961534,"remaining_time":145.0700153},
{"learn":[0.7607077249],"iteration":186,"passed_time":52.7625001,"remaining_time":144.7441848},
{"learn":[0.7604892372],"iteration":187,"passed_time":53.03478691,"remaining_time":144.4351644},
{"learn":[0.760325403],"iteration":188,"passed_time":53.29799009,"remaining_time":144.1019732},
{"learn":[0.7601720846],"iteration":189,"passed_time":53.56130142,"remaining_time":143.7698091},
{"learn":[0.7598282376],"iteration":190,"passed_time":53.84717556,"remaining_time":143.498494},
{"learn":[0.7596347485],"iteration":191,"passed_time":54.11821871,"remaining_time":143.187787},
{"learn":[0.7594013525],"iteration":192,"passed_time":54.39829217,"remaining_time":142.9012131},
{"learn":[0.7592651185],"iteration":193,"passed_time":54.65906817,"remaining_time":142.5643737},
{"learn":[0.7590562857],"iteration":194,"passed_time":54.92392464,"remaining_time":142.2388818},
{"learn":[0.7588454992],"iteration":195,"passed_time":55.19461005,"remaining_time":141.9289973},
{"learn":[0.7586555184],"iteration":196,"passed_time":55.46733901,"remaining_time":141.6247285},
{"learn":[0.7584301596],"iteration":197,"passed_time":55.75667849,"remaining_time":141.3628919},
{"learn":[0.7582846738],"iteration":198,"passed_time":56.03439758,"remaining_time":141.0715235},
{"learn":[0.7581010775],"iteration":199,"passed_time":56.31089866,"remaining_time":140.7772467},
{"learn":[0.7579213445],"iteration":200,"passed_time":56.5840628,"remaining_time":140.4748624},
{"learn":[0.7577722051],"iteration":201,"passed_time":56.84908463,"remaining_time":140.1526938},
{"learn":[0.7575354779],"iteration":202,"passed_time":57.12266458,"remaining_time":139.8520409},
{"learn":[0.7572877743],"iteration":203,"passed_time":57.40044362,"remaining_time":139.5618629},
{"learn":[0.7571235612],"iteration":204,"passed_time":57.67717423,"remaining_time":139.2692744},
{"learn":[0.7569608894],"iteration":205,"passed_time":57.94490493,"remaining_time":138.9552575},
{"learn":[0.7567984122],"iteration":206,"passed_time":58.20507602,"remaining_time":138.6236835},
{"learn":[0.7564750551],"iteration":207,"passed_time":58.53196478,"remaining_time":138.450609},
{"learn":[0.7563270571],"iteration":208,"passed_time":58.8031784,"remaining_time":138.145266},
{"learn":[0.7560974582],"iteration":209,"passed_time":59.07469459,"remaining_time":137.840954},
{"learn":[0.7558054608],"iteration":210,"passed_time":59.35879251,"remaining_time":137.5661116},
{"learn":[0.7556602244],"iteration":211,"passed_time":59.61955085,"remaining_time":137.2374567},
{"learn":[0.7554758778],"iteration":212,"passed_time":59.90314031,"remaining_time":136.9616401},
{"learn":[0.7552757324],"iteration":213,"passed_time":60.18282808,"remaining_time":136.6768899},
{"learn":[0.7551418125],"iteration":214,"passed_time":60.44757301,"remaining_time":136.3584787},
{"learn":[0.7548384212],"iteration":215,"passed_time":60.72942376,"remaining_time":136.078894},
{"learn":[0.7546540507],"iteration":216,"passed_time":60.99983447,"remaining_time":135.7738251},
{"learn":[0.7544480674],"iteration":217,"passed_time":61.28184641,"remaining_time":135.4947246},
{"learn":[0.7542380302],"iteration":218,"passed_time":61.5606977,"remaining_time":135.2086557},
{"learn":[0.7541402577],"iteration":219,"passed_time":61.83773807,"remaining_time":134.9187012},
{"learn":[0.7540140114],"iteration":220,"passed_time":62.09837015,"remaining_time":134.5933},
{"learn":[0.7538208706],"iteration":221,"passed_time":62.38087249,"remaining_time":134.3155723},
{"learn":[0.7537086868],"iteration":222,"passed_time":62.67006055,"remaining_time":134.0521026},
{"learn":[0.7535152903],"iteration":223,"passed_time":62.94453825,"remaining_time":133.7571438},
{"learn":[0.7533662648],"iteration":224,"passed_time":63.230579,"remaining_time":133.4867779},
{"learn":[0.7532201686],"iteration":225,"passed_time":63.50079131,"remaining_time":133.1830756},
{"learn":[0.7530918122],"iteration":226,"passed_time":63.76212465,"remaining_time":132.8611672},
{"learn":[0.7528408341],"iteration":227,"passed_time":64.04254978,"remaining_time":132.5793136},
{"learn":[0.7526546586],"iteration":228,"passed_time":64.35119647,"remaining_time":132.3555176},
{"learn":[0.7524937433],"iteration":229,"passed_time":64.61790584,"remaining_time":132.0452858},
{"learn":[0.7522624376],"iteration":230,"passed_time":64.90245755,"remaining_time":131.7716562},
{"learn":[0.7520584417],"iteration":231,"passed_time":65.18226164,"remaining_time":131.4883554},
{"learn":[0.7518162785],"iteration":232,"passed_time":65.46896448,"remaining_time":131.2189116},
{"learn":[0.7516447865],"iteration":233,"passed_time":65.73758594,"remaining_time":130.9133122},
{"learn":[0.7514589515],"iteration":234,"passed_time":66.00623768,"remaining_time":130.6080873},
{"learn":[0.7512650405],"iteration":235,"passed_time":66.28717606,"remaining_time":130.3273292},
{"learn":[0.7511610125],"iteration":236,"passed_time":66.54838368,"remaining_time":130.0080238},
{"learn":[0.7509676531],"iteration":237,"passed_time":66.82496745,"remaining_time":129.7190545},
{"learn":[0.750888931],"iteration":238,"passed_time":67.08410443,"remaining_time":129.3965362},
{"learn":[0.7507338922],"iteration":239,"passed_time":67.35604409,"remaining_time":129.0990845},
{"learn":[0.7505408036],"iteration":240,"passed_time":67.63131583,"remaining_time":128.8081907},
{"learn":[0.7504654308],"iteration":241,"passed_time":67.89384945,"remaining_time":128.4933184},
{"learn":[0.7502868616],"iteration":242,"passed_time":68.16543666,"remaining_time":128.1959035},
{"learn":[0.7500623314],"iteration":243,"passed_time":68.4655048,"remaining_time":127.951927},
{"learn":[0.7499413517],"iteration":244,"passed_time":68.73210191,"remaining_time":127.6453321},
{"learn":[0.7496676506],"iteration":245,"passed_time":69.02145175,"remaining_time":127.3810532},
{"learn":[0.7495029874],"iteration":246,"passed_time":69.29585092,"remaining_time":127.0891517},
{"learn":[0.7493375857],"iteration":247,"passed_time":69.58064574,"remaining_time":126.8163382},
{"learn":[0.7492101319],"iteration":248,"passed_time":69.84721695,"remaining_time":126.5104211},
{"learn":[0.7490509627],"iteration":249,"passed_time":70.1229933,"remaining_time":126.2213879},
{"learn":[0.7488424067],"iteration":250,"passed_time":70.39743319,"remaining_time":125.9300697},
{"learn":[0.7486819755],"iteration":251,"passed_time":70.67806899,"remaining_time":125.6499004},
{"learn":[0.7485024954],"iteration":252,"passed_time":70.95459185,"remaining_time":125.3624607},
{"learn":[0.748367809],"iteration":253,"passed_time":71.23507876,"remaining_time":125.0820674},
{"learn":[0.7482043826],"iteration":254,"passed_time":71.51900489,"remaining_time":124.8076752},
{"learn":[0.7480461351],"iteration":255,"passed_time":71.78305829,"remaining_time":124.4987417},
{"learn":[0.7479085452],"iteration":256,"passed_time":72.05977331,"remaining_time":124.2119828},
{"learn":[0.7477354427],"iteration":257,"passed_time":72.3266537,"remaining_time":123.9084532},
{"learn":[0.7475398028],"iteration":258,"passed_time":72.6053767,"remaining_time":123.6253711},
{"learn":[0.747360371],"iteration":259,"passed_time":72.88060704,"remaining_time":123.3364119},
{"learn":[0.7472189291],"iteration":260,"passed_time":73.14237564,"remaining_time":123.0249154},
{"learn":[0.7470464827],"iteration":261,"passed_time":73.4005944,"remaining_time":122.7078639},
{"learn":[0.7468689956],"iteration":262,"passed_time":73.6813687,"remaining_time":122.4287381},
{"learn":[0.7467092707],"iteration":263,"passed_time":73.95124785,"remaining_time":122.1316063},
{"learn":[0.7464338304],"iteration":264,"passed_time":74.23890013,"remaining_time":121.8638549},
{"learn":[0.7462427492],"iteration":265,"passed_time":74.50883285,"remaining_time":121.5670431},
{"learn":[0.7460793915],"iteration":266,"passed_time":74.78241327,"remaining_time":121.2763481},
{"learn":[0.7458737409],"iteration":267,"passed_time":75.05361036,"remaining_time":120.9819391},
{"learn":[0.7456396318],"iteration":268,"passed_time":75.33292952,"remaining_time":120.7007161},
{"learn":[0.7454355812],"iteration":269,"passed_time":75.62655726,"remaining_time":120.4422949},
{"learn":[0.7452574721],"iteration":270,"passed_time":75.91943399,"remaining_time":120.182425},
{"learn":[0.7451075593],"iteration":271,"passed_time":76.19934113,"remaining_time":119.9019044},
{"learn":[0.7448761316],"iteration":272,"passed_time":76.48719177,"remaining_time":119.6338128},
{"learn":[0.7447105741],"iteration":273,"passed_time":76.75344887,"remaining_time":119.3320044},
{"learn":[0.7445179546],"iteration":274,"passed_time":77.02896277,"remaining_time":119.0447606},
{"learn":[0.7444029299],"iteration":275,"passed_time":77.29288099,"remaining_time":118.7397882},
{"learn":[0.7442720722],"iteration":276,"passed_time":77.55926781,"remaining_time":118.4388819},
{"learn":[0.7441626857],"iteration":277,"passed_time":77.82546073,"remaining_time":118.1379296},
{"learn":[0.7440024267],"iteration":278,"passed_time":78.0988167,"remaining_time":117.8480352},
{"learn":[0.7439162402],"iteration":279,"passed_time":78.35255655,"remaining_time":117.5288348},
{"learn":[0.7437615114],"iteration":280,"passed_time":78.61966523,"remaining_time":117.2300346},
{"learn":[0.7436237986],"iteration":281,"passed_time":78.8834797,"remaining_time":116.9265763},
{"learn":[0.7434921376],"iteration":282,"passed_time":79.14816358,"remaining_time":116.6246792},
{"learn":[0.7433800386],"iteration":283,"passed_time":79.41615675,"remaining_time":116.3278916},
{"learn":[0.7431810168],"iteration":284,"passed_time":79.71173427,"remaining_time":116.0714727},
{"learn":[0.7429880019],"iteration":285,"passed_time":79.99772129,"remaining_time":115.8008972},
{"learn":[0.7429002399],"iteration":286,"passed_time":80.27198765,"remaining_time":115.5133481},
{"learn":[0.7427269942],"iteration":287,"passed_time":80.54755699,"remaining_time":115.2277551},
{"learn":[0.7425659235],"iteration":288,"passed_time":80.83514971,"remaining_time":114.9593305},
{"learn":[0.7424152653],"iteration":289,"passed_time":81.13151361,"remaining_time":114.7031744},
{"learn":[0.7422594614],"iteration":290,"passed_time":81.41735651,"remaining_time":114.4319547},
{"learn":[0.742080775],"iteration":291,"passed_time":81.71252517,"remaining_time":114.1736653},
{"learn":[0.7419302369],"iteration":292,"passed_time":81.99123285,"remaining_time":113.8922586},
{"learn":[0.7417738016],"iteration":293,"passed_time":82.25277094,"remaining_time":113.5871599},
{"learn":[0.7415945205],"iteration":294,"passed_time":82.53398107,"remaining_time":113.3093638},
{"learn":[0.7413957247],"iteration":295,"passed_time":82.84649095,"remaining_time":113.0742647},
{"learn":[0.7410869405],"iteration":296,"passed_time":83.14499532,"remaining_time":112.8196401},
{"learn":[0.7408619575],"iteration":297,"passed_time":83.42195322,"remaining_time":112.535655},
{"learn":[0.7406399712],"iteration":298,"passed_time":83.70447511,"remaining_time":112.259179},
{"learn":[0.7404424006],"iteration":299,"passed_time":83.99543519,"remaining_time":111.9939136},
{"learn":[0.7402718793],"iteration":300,"passed_time":84.2878226,"remaining_time":111.7303695},
{"learn":[0.7400792098],"iteration":301,"passed_time":84.56674123,"remaining_time":111.4488841},
{"learn":[0.7399620271],"iteration":302,"passed_time":84.84207233,"remaining_time":111.1627152},
{"learn":[0.739812651],"iteration":303,"passed_time":85.1174378,"remaining_time":110.8766624},
{"learn":[0.7396105227],"iteration":304,"passed_time":85.3859924,"remaining_time":110.581859},
{"learn":[0.7394074219],"iteration":305,"passed_time":85.65417286,"remaining_time":110.2867454},
{"learn":[0.7392088178],"iteration":306,"passed_time":85.9371199,"remaining_time":110.0107105},
{"learn":[0.7389983265],"iteration":307,"passed_time":86.23127276,"remaining_time":109.7488926},
{"learn":[0.7388383581],"iteration":308,"passed_time":86.52034425,"remaining_time":109.4804356},
{"learn":[0.7385815008],"iteration":309,"passed_time":86.80582549,"remaining_time":109.2073288},
{"learn":[0.7385032022],"iteration":310,"passed_time":87.06113076,"remaining_time":108.8963983},
{"learn":[0.7383854745],"iteration":311,"passed_time":87.33118119,"remaining_time":108.6041612},
{"learn":[0.7382259523],"iteration":312,"passed_time":87.61427543,"remaining_time":108.3281936},
{"learn":[0.738096548],"iteration":313,"passed_time":87.88362574,"remaining_time":108.0352851},
{"learn":[0.7379163907],"iteration":314,"passed_time":88.15489823,"remaining_time":107.7448756},
{"learn":[0.7378156752],"iteration":315,"passed_time":88.41634214,"remaining_time":107.4426436},
{"learn":[0.7376205435],"iteration":316,"passed_time":88.70606924,"remaining_time":107.1748408},
{"learn":[0.7374746822],"iteration":317,"passed_time":88.99061653,"remaining_time":106.9006777},
{"learn":[0.7373673994],"iteration":318,"passed_time":89.25888481,"remaining_time":106.6070066},
{"learn":[0.7371924513],"iteration":319,"passed_time":89.53361616,"remaining_time":106.3211692},
{"learn":[0.7370951572],"iteration":320,"passed_time":89.79887042,"remaining_time":106.0242115},
{"learn":[0.73699383],"iteration":321,"passed_time":90.05888851,"remaining_time":105.7213039},
{"learn":[0.7368993946],"iteration":322,"passed_time":90.32048292,"remaining_time":105.4205017},
{"learn":[0.7367798957],"iteration":323,"passed_time":90.61596127,"remaining_time":105.1592637},
{"learn":[0.7366562568],"iteration":324,"passed_time":90.88348821,"remaining_time":104.8655633},
{"learn":[0.7365427939],"iteration":325,"passed_time":91.1533656,"remaining_time":104.57472},
{"learn":[0.736355016],"iteration":326,"passed_time":91.43601028,"remaining_time":104.2985683},
{"learn":[0.7362101546],"iteration":327,"passed_time":91.71559167,"remaining_time":104.0189028},
{"learn":[0.7361122244],"iteration":328,"passed_time":91.99756766,"remaining_time":103.741938},
{"learn":[0.7359942333],"iteration":329,"passed_time":92.2753485,"remaining_time":103.4602392},
{"learn":[0.7358234017],"iteration":330,"passed_time":92.55399648,"remaining_time":103.1795308},
{"learn":[0.7356621697],"iteration":331,"passed_time":92.83257407,"remaining_time":102.8987568},
{"learn":[0.7354809788],"iteration":332,"passed_time":93.12112524,"remaining_time":102.6289879},
{"learn":[0.7353249042],"iteration":333,"passed_time":93.39711141,"remaining_time":102.3453376},
{"learn":[0.7351759499],"iteration":334,"passed_time":93.67534968,"remaining_time":102.064187},
{"learn":[0.734990673],"iteration":335,"passed_time":93.95524733,"remaining_time":101.7848513},
{"learn":[0.7348609489],"iteration":336,"passed_time":94.21843372,"remaining_time":101.4875117},
{"learn":[0.7346998278],"iteration":337,"passed_time":94.49775716,"remaining_time":101.2076571},
{"learn":[0.734486218],"iteration":338,"passed_time":94.78298319,"remaining_time":100.9340912},
{"learn":[0.7343884956],"iteration":339,"passed_time":95.05237665,"remaining_time":100.6436929},
{"learn":[0.7342693586],"iteration":340,"passed_time":95.32583843,"remaining_time":100.3577009},
{"learn":[0.73416195],"iteration":341,"passed_time":95.58854267,"remaining_time":100.0605213},
{"learn":[0.7340820386],"iteration":342,"passed_time":95.85933982,"remaining_time":99.77196594},
{"learn":[0.7339308719],"iteration":343,"passed_time":96.12952828,"remaining_time":99.48288392},
{"learn":[0.7337665024],"iteration":344,"passed_time":96.40735963,"remaining_time":99.20177586},
{"learn":[0.7335148687],"iteration":345,"passed_time":96.69669263,"remaining_time":98.93245431},
{"learn":[0.7334115492],"iteration":346,"passed_time":97.08175902,"remaining_time":98.76040615},
{"learn":[0.7331982899],"iteration":347,"passed_time":97.36501785,"remaining_time":98.48415598},
{"learn":[0.7329941444],"iteration":348,"passed_time":97.65607353,"remaining_time":98.21570719},
{"learn":[0.7328685576],"iteration":349,"passed_time":97.92431912,"remaining_time":97.92431912},
{"learn":[0.732688811],"iteration":350,"passed_time":98.19454681,"remaining_time":97.63503372},
{"learn":[0.732591514],"iteration":351,"passed_time":98.4536916,"remaining_time":97.33489965},
{"learn":[0.7324448275],"iteration":352,"passed_time":98.72665489,"remaining_time":97.04858143},
{"learn":[0.732311406],"iteration":353,"passed_time":99.005552,"remaining_time":96.7681384},
{"learn":[0.7321439974],"iteration":354,"passed_time":99.27906415,"remaining_time":96.48247079},
{"learn":[0.7320402348],"iteration":355,"passed_time":99.54681441,"remaining_time":96.19130381},
{"learn":[0.7318511579],"iteration":356,"passed_time":99.82649592,"remaining_time":95.91173138},
{"learn":[0.7317426423],"iteration":357,"passed_time":100.1165573,"remaining_time":95.64207433},
{"learn":[0.7315598078],"iteration":358,"passed_time":100.3939866,"remaining_time":95.36030484},
{"learn":[0.7313776001],"iteration":359,"passed_time":100.6663148,"remaining_time":95.07374177},
{"learn":[0.7311709124],"iteration":360,"passed_time":100.937961,"remaining_time":94.78661711},
{"learn":[0.7310126923],"iteration":361,"passed_time":101.2153421,"remaining_time":94.50493271},
{"learn":[0.7308848226],"iteration":362,"passed_time":101.4818384,"remaining_time":94.21316674},
{"learn":[0.7307622023],"iteration":363,"passed_time":101.7378025,"remaining_time":93.91181766},
{"learn":[0.730637027],"iteration":364,"passed_time":102.0116496,"remaining_time":93.62713048},
{"learn":[0.7305200026],"iteration":365,"passed_time":102.2745812,"remaining_time":93.3325413},
{"learn":[0.7303939121],"iteration":366,"passed_time":102.5408165,"remaining_time":93.04112233},
{"learn":[0.7302647638],"iteration":367,"passed_time":102.8022564,"remaining_time":92.74551388},
{"learn":[0.7300831848],"iteration":368,"passed_time":103.0783936,"remaining_time":92.4632745},
{"learn":[0.7298596704],"iteration":369,"passed_time":103.376557,"remaining_time":92.20071303},
{"learn":[0.7296602177],"iteration":370,"passed_time":103.6561938,"remaining_time":91.92153036},
{"learn":[0.7295202021],"iteration":371,"passed_time":103.9356019,"remaining_time":91.64214363},
{"learn":[0.7293886439],"iteration":372,"passed_time":104.2059871,"remaining_time":91.35484657},
{"learn":[0.729280719],"iteration":373,"passed_time":104.4650693,"remaining_time":91.05778768},
{"learn":[0.7290751348],"iteration":374,"passed_time":104.7512802,"remaining_time":90.78444284},
{"learn":[0.7288688063],"iteration":375,"passed_time":105.032464,"remaining_time":90.50669769},
{"learn":[0.7287279321],"iteration":376,"passed_time":105.2956877,"remaining_time":90.21354673},
{"learn":[0.7285799555],"iteration":377,"passed_time":105.5740596,"remaining_time":89.9334582},
{"learn":[0.7284336242],"iteration":378,"passed_time":105.8516055,"remaining_time":89.65267909},
{"learn":[0.7283099657],"iteration":379,"passed_time":106.1443251,"remaining_time":89.38469482},
{"learn":[0.7281952763],"iteration":380,"passed_time":106.4109746,"remaining_time":89.09475297},
{"learn":[0.7280482894],"iteration":381,"passed_time":106.683506,"remaining_time":88.80982958},
{"learn":[0.7278725512],"iteration":382,"passed_time":106.9576473,"remaining_time":88.52630338},
{"learn":[0.7277391977],"iteration":383,"passed_time":107.2351639,"remaining_time":88.24560365},
{"learn":[0.727604317],"iteration":384,"passed_time":107.5034277,"remaining_time":87.95734995},
{"learn":[0.7274960547],"iteration":385,"passed_time":107.7667459,"remaining_time":87.6651767},
{"learn":[0.7273364448],"iteration":386,"passed_time":108.0409838,"remaining_time":87.38198433},
{"learn":[0.7271531295],"iteration":387,"passed_time":108.3226483,"remaining_time":87.10480997},
{"learn":[0.7270520756],"iteration":388,"passed_time":108.5905092,"remaining_time":86.8165768},
{"learn":[0.7269357925],"iteration":389,"passed_time":108.8562052,"remaining_time":86.52672719},
{"learn":[0.7268004405],"iteration":390,"passed_time":109.1493659,"remaining_time":86.25870607},
{"learn":[0.7266671758],"iteration":391,"passed_time":109.4250539,"remaining_time":85.97682807},
{"learn":[0.7265513133],"iteration":392,"passed_time":109.6890557,"remaining_time":85.68585268},
{"learn":[0.7264164243],"iteration":393,"passed_time":109.955178,"remaining_time":85.39666108},
{"learn":[0.7261983816],"iteration":394,"passed_time":110.2435987,"remaining_time":85.12480409},
{"learn":[0.726011642],"iteration":395,"passed_time":110.5135789,"remaining_time":84.83870707},
{"learn":[0.725887517],"iteration":396,"passed_time":110.7825117,"remaining_time":84.5518918},
{"learn":[0.725739877],"iteration":397,"passed_time":111.0555879,"remaining_time":84.26831044},
{"learn":[0.7256079458],"iteration":398,"passed_time":111.3352416,"remaining_time":83.98974363},
{"learn":[0.7254498429],"iteration":399,"passed_time":111.605813,"remaining_time":83.70435972},
{"learn":[0.7253303448],"iteration":400,"passed_time":111.8732256,"remaining_time":83.41669439},
{"learn":[0.7251303609],"iteration":401,"passed_time":112.1757321,"remaining_time":83.15514465},
{"learn":[0.7249979325],"iteration":402,"passed_time":112.4611905,"remaining_time":82.88082774},
{"learn":[0.724726433],"iteration":403,"passed_time":112.7502372,"remaining_time":82.60908469},
{"learn":[0.7245795004],"iteration":404,"passed_time":113.050601,"remaining_time":82.34549946},
{"learn":[0.7244534185],"iteration":405,"passed_time":113.3151448,"remaining_time":82.05579455},
{"learn":[0.7243171777],"iteration":406,"passed_time":113.5859718,"remaining_time":81.77073642},
{"learn":[0.7241821641],"iteration":407,"passed_time":113.8617854,"remaining_time":81.48931702},
{"learn":[0.72403619],"iteration":408,"passed_time":114.1361132,"remaining_time":81.20686784},
{"learn":[0.7238486649],"iteration":409,"passed_time":114.4119796,"remaining_time":80.92554652},
{"learn":[0.723634053],"iteration":410,"passed_time":114.6861952,"remaining_time":80.64309101},
{"learn":[0.7234621749],"iteration":411,"passed_time":114.9578506,"remaining_time":80.35888586},
{"learn":[0.7232624336],"iteration":412,"passed_time":115.2469677,"remaining_time":80.08687584},
{"learn":[0.7230871852],"iteration":413,"passed_time":115.5257556,"remaining_time":79.80764761},
{"learn":[0.7229071965],"iteration":414,"passed_time":115.7955046,"remaining_time":79.52221403},
{"learn":[0.7227677395],"iteration":415,"passed_time":116.0741607,"remaining_time":79.24293662},
{"learn":[0.7226120376],"iteration":416,"passed_time":116.344742,"remaining_time":78.95818222},
{"learn":[0.722477814],"iteration":417,"passed_time":116.6191961,"remaining_time":78.6761084},
{"learn":[0.7222740406],"iteration":418,"passed_time":116.8956389,"remaining_time":78.3954046},
{"learn":[0.7220844098],"iteration":419,"passed_time":117.1707893,"remaining_time":78.11385952},
{"learn":[0.7219654489],"iteration":420,"passed_time":117.4356402,"remaining_time":77.82551925},
{"learn":[0.7217917532],"iteration":421,"passed_time":117.7131012,"remaining_time":77.54559746},
{"learn":[0.7216861087],"iteration":422,"passed_time":117.9728387,"remaining_time":77.25408112},
{"learn":[0.7215262058],"iteration":423,"passed_time":118.243299,"remaining_time":76.96969462},
{"learn":[0.7213690634],"iteration":424,"passed_time":118.5138237,"remaining_time":76.68541536},
{"learn":[0.7211582549],"iteration":425,"passed_time":118.80691,"remaining_time":76.41571205},
{"learn":[0.7210324137],"iteration":426,"passed_time":119.0680391,"remaining_time":76.1254676},
{"learn":[0.7208246997],"iteration":427,"passed_time":119.3569912,"remaining_time":75.85304112},
{"learn":[0.7206527117],"iteration":428,"passed_time":119.6330454,"remaining_time":75.57238999},
{"learn":[0.720533429],"iteration":429,"passed_time":119.9052413,"remaining_time":75.28933755},
{"learn":[0.7203501939],"iteration":430,"passed_time":120.1886311,"remaining_time":75.01332198},
{"learn":[0.7202190364],"iteration":431,"passed_time":120.4471885,"remaining_time":74.72186691},
{"learn":[0.7200596509],"iteration":432,"passed_time":120.7441377,"remaining_time":74.45423735},
{"learn":[0.7199274236],"iteration":433,"passed_time":121.0092353,"remaining_time":74.16695068},
{"learn":[0.7197739678],"iteration":434,"passed_time":121.2894813,"remaining_time":73.88899436},
{"learn":[0.7196488143],"iteration":435,"passed_time":121.5632232,"remaining_time":73.60708927},
{"learn":[0.719496202],"iteration":436,"passed_time":121.8382529,"remaining_time":73.32599658},
{"learn":[0.7193761619],"iteration":437,"passed_time":122.1131267,"remaining_time":73.04483836},
{"learn":[0.7192302587],"iteration":438,"passed_time":122.3740099,"remaining_time":72.75539088},
{"learn":[0.7190952871],"iteration":439,"passed_time":122.6478727,"remaining_time":72.47374296},
{"learn":[0.7189875585],"iteration":440,"passed_time":122.9015496,"remaining_time":72.18027518},
{"learn":[0.7188330101],"iteration":441,"passed_time":123.1820186,"remaining_time":71.90262623},
{"learn":[0.7187076412],"iteration":442,"passed_time":123.4517884,"remaining_time":71.61875763},
{"learn":[0.7185231836],"iteration":443,"passed_time":123.733666,"remaining_time":71.34193354},
{"learn":[0.7184161059],"iteration":444,"passed_time":123.9993694,"remaining_time":71.0558184},
{"learn":[0.7183412756],"iteration":445,"passed_time":124.2685312,"remaining_time":70.7717644},
{"learn":[0.71818291],"iteration":446,"passed_time":124.5424739,"remaining_time":70.490483},
{"learn":[0.7179982489],"iteration":447,"passed_time":124.8141508,"remaining_time":70.20795984},
{"learn":[0.7178710102],"iteration":448,"passed_time":125.1026006,"remaining_time":69.93486137},
{"learn":[0.7176900971],"iteration":449,"passed_time":125.3795772,"remaining_time":69.65532069},
{"learn":[0.7175639874],"iteration":450,"passed_time":125.6510538,"remaining_time":69.37275475},
{"learn":[0.7173678186],"iteration":451,"passed_time":125.9477826,"remaining_time":69.10409312},
{"learn":[0.7172049747],"iteration":452,"passed_time":126.2121653,"remaining_time":68.81767073},
{"learn":[0.717099692],"iteration":453,"passed_time":126.4683561,"remaining_time":68.52690663},
{"learn":[0.7169843653],"iteration":454,"passed_time":126.7366488,"remaining_time":68.24281092},
{"learn":[0.7168587409],"iteration":455,"passed_time":127.0203195,"remaining_time":67.96701308},
{"learn":[0.7166931767],"iteration":456,"passed_time":127.3224776,"remaining_time":67.70101106},
{"learn":[0.7165130981],"iteration":457,"passed_time":127.6073764,"remaining_time":67.42573165},
{"learn":[0.7162756638],"iteration":458,"passed_time":127.9107999,"remaining_time":67.16013676},
{"learn":[0.7161311581],"iteration":459,"passed_time":128.1749246,"remaining_time":66.87387371},
{"learn":[0.716014729],"iteration":460,"passed_time":128.436126,"remaining_time":66.58619112},
{"learn":[0.7158730088],"iteration":461,"passed_time":128.7068169,"remaining_time":66.30351173},
{"learn":[0.7156811759],"iteration":462,"passed_time":129.0016586,"remaining_time":66.03324641},
{"learn":[0.7155274625],"iteration":463,"passed_time":129.2727565,"remaining_time":65.75079857},
{"learn":[0.7154113854],"iteration":464,"passed_time":129.549912,"remaining_time":65.4714609},
{"learn":[0.7153025905],"iteration":465,"passed_time":129.8114156,"remaining_time":65.18427305},
{"learn":[0.7150985842],"iteration":466,"passed_time":130.0994637,"remaining_time":64.91043908},
{"learn":[0.7149980096],"iteration":467,"passed_time":130.3785285,"remaining_time":64.63209107},
{"learn":[0.7148881414],"iteration":468,"passed_time":130.6368584,"remaining_time":64.34352727},
{"learn":[0.7147212948],"iteration":469,"passed_time":130.906442,"remaining_time":64.0605993},
{"learn":[0.714563766],"iteration":470,"passed_time":131.2343745,"remaining_time":63.80609717},
{"learn":[0.7144306186],"iteration":471,"passed_time":131.5106305,"remaining_time":63.52632153},
{"learn":[0.7142638011],"iteration":472,"passed_time":131.799695,"remaining_time":63.25270774},
{"learn":[0.7141541267],"iteration":473,"passed_time":132.0744006,"remaining_time":62.97218259},
{"learn":[0.7140015728],"iteration":474,"passed_time":132.3440122,"remaining_time":62.68926894},
{"learn":[0.7138662034],"iteration":475,"passed_time":132.6253831,"remaining_time":62.41194499},
{"learn":[0.7137373791],"iteration":476,"passed_time":132.8917217,"remaining_time":62.12757637},
{"learn":[0.7135785381],"iteration":477,"passed_time":133.1788078,"remaining_time":61.8529191},
{"learn":[0.7134854902],"iteration":478,"passed_time":133.4513884,"remaining_time":61.57151741},
{"learn":[0.7133613948],"iteration":479,"passed_time":133.7142894,"remaining_time":61.28571597},
{"learn":[0.7132326055],"iteration":480,"passed_time":134.0004139,"remaining_time":61.01058345},
{"learn":[0.7130862359],"iteration":481,"passed_time":134.2713358,"remaining_time":60.72852948},
{"learn":[0.7129830925],"iteration":482,"passed_time":134.5310531,"remaining_time":60.44148764},
{"learn":[0.7128319494],"iteration":483,"passed_time":134.8093655,"remaining_time":60.16285732},
{"learn":[0.7126370319],"iteration":484,"passed_time":135.0842881,"remaining_time":59.88272563},
{"learn":[0.7124830874],"iteration":485,"passed_time":135.3671803,"remaining_time":59.60612466},
{"learn":[0.7123300238],"iteration":486,"passed_time":135.6354922,"remaining_time":59.32312083},
{"learn":[0.7121930955],"iteration":487,"passed_time":135.9295514,"remaining_time":59.0513625},
{"learn":[0.7120621231],"iteration":488,"passed_time":136.1967461,"remaining_time":58.76792113},
{"learn":[0.7119634007],"iteration":489,"passed_time":136.4549025,"remaining_time":58.4806725},
{"learn":[0.711853567],"iteration":490,"passed_time":136.7221554,"remaining_time":58.19741442},
{"learn":[0.7117246885],"iteration":491,"passed_time":136.9800409,"remaining_time":57.9102612},
{"learn":[0.7115896476],"iteration":492,"passed_time":137.2459875,"remaining_time":57.62661138},
{"learn":[0.7114309702],"iteration":493,"passed_time":137.5244323,"remaining_time":57.34824505},
{"learn":[0.7113276523],"iteration":494,"passed_time":137.7888066,"remaining_time":57.06405121},
{"learn":[0.711184266],"iteration":495,"passed_time":138.0644347,"remaining_time":56.78456588},
{"learn":[0.711076943],"iteration":496,"passed_time":138.3218528,"remaining_time":56.49765817},
{"learn":[0.7109671581],"iteration":497,"passed_time":138.5908633,"remaining_time":56.21557104},
{"learn":[0.7107958117],"iteration":498,"passed_time":138.8684083,"remaining_time":55.93697408},
{"learn":[0.7106882757],"iteration":499,"passed_time":139.1311175,"remaining_time":55.65244701},
{"learn":[0.710534222],"iteration":500,"passed_time":139.4209544,"remaining_time":55.37878229},
{"learn":[0.7104126439],"iteration":501,"passed_time":139.7056532,"remaining_time":55.10302658},
{"learn":[0.710267574],"iteration":502,"passed_time":139.976182,"remaining_time":54.82168559},
{"learn":[0.7101158455],"iteration":503,"passed_time":140.2645456,"remaining_time":54.5473233},
{"learn":[0.7099930283],"iteration":504,"passed_time":140.5354131,"remaining_time":54.26614963},
{"learn":[0.7098281335],"iteration":505,"passed_time":140.8269198,"remaining_time":53.99292973},
{"learn":[0.7097005998],"iteration":506,"passed_time":141.1120612,"remaining_time":53.7172146},
{"learn":[0.7095878932],"iteration":507,"passed_time":141.4321968,"remaining_time":53.45468854},
{"learn":[0.7094776329],"iteration":508,"passed_time":141.7260961,"remaining_time":53.18209105},
{"learn":[0.7093397895],"iteration":509,"passed_time":142.0209874,"remaining_time":52.90977961},
{"learn":[0.7091880522],"iteration":510,"passed_time":142.3156214,"remaining_time":52.63728461},
{"learn":[0.7090266141],"iteration":511,"passed_time":142.6176732,"remaining_time":52.36742686},
{"learn":[0.7089181527],"iteration":512,"passed_time":142.9185656,"remaining_time":52.09702098},
{"learn":[0.7087934248],"iteration":513,"passed_time":143.215235,"remaining_time":51.82496832},
{"learn":[0.7086824544],"iteration":514,"passed_time":143.5052348,"remaining_time":51.55042416},
{"learn":[0.7085514418],"iteration":515,"passed_time":143.7760818,"remaining_time":51.2689904},
{"learn":[0.7084517758],"iteration":516,"passed_time":144.0346189,"remaining_time":50.98324036},
{"learn":[0.7083426438],"iteration":517,"passed_time":144.3205318,"remaining_time":50.70721388},
{"learn":[0.7081847764],"iteration":518,"passed_time":144.5999541,"remaining_time":50.42888574},
{"learn":[0.7080882454],"iteration":519,"passed_time":144.8606629,"remaining_time":50.14407563},
{"learn":[0.7079069588],"iteration":520,"passed_time":145.1488354,"remaining_time":49.86879374},
{"learn":[0.7078102676],"iteration":521,"passed_time":145.4125926,"remaining_time":49.58513694},
{"learn":[0.7077216285],"iteration":522,"passed_time":145.6805662,"remaining_time":49.3029832},
{"learn":[0.7076150714],"iteration":523,"passed_time":145.9546191,"remaining_time":49.02292551},
{"learn":[0.7074903138],"iteration":524,"passed_time":146.2265571,"remaining_time":48.7421857},
{"learn":[0.7073785237],"iteration":525,"passed_time":146.4868012,"remaining_time":48.45761103},
{"learn":[0.7072640737],"iteration":526,"passed_time":146.7684055,"remaining_time":48.18014069},
{"learn":[0.7071651323],"iteration":527,"passed_time":147.0364286,"remaining_time":47.89823054},
{"learn":[0.7069816765],"iteration":528,"passed_time":147.3235756,"remaining_time":47.62255469},
{"learn":[0.7068735996],"iteration":529,"passed_time":147.6021259,"remaining_time":47.34407811},
{"learn":[0.7067761195],"iteration":530,"passed_time":147.8639165,"remaining_time":47.06026722},
{"learn":[0.7066849623],"iteration":531,"passed_time":148.1194303,"remaining_time":46.77455694},
{"learn":[0.7065931836],"iteration":532,"passed_time":148.3808041,"remaining_time":46.49079604},
{"learn":[0.7064350555],"iteration":533,"passed_time":148.6558661,"remaining_time":46.21137411},
{"learn":[0.7063178123],"iteration":534,"passed_time":148.9285251,"remaining_time":45.93122737},
{"learn":[0.7061689076],"iteration":535,"passed_time":149.2043717,"remaining_time":45.65208388},
{"learn":[0.7060327904],"iteration":536,"passed_time":149.4792805,"remaining_time":45.372668},
{"learn":[0.705899608],"iteration":537,"passed_time":149.7523833,"remaining_time":45.09272508},
{"learn":[0.7057754716],"iteration":538,"passed_time":150.0411895,"remaining_time":44.81749816},
{"learn":[0.7056423318],"iteration":539,"passed_time":150.3467588,"remaining_time":44.54718778},
{"learn":[0.7055353319],"iteration":540,"passed_time":150.6322745,"remaining_time":44.27085331},
{"learn":[0.705444924],"iteration":541,"passed_time":150.8949314,"remaining_time":43.98782134},
{"learn":[0.7052641358],"iteration":542,"passed_time":151.1712659,"remaining_time":43.70881906},
{"learn":[0.7051598189],"iteration":543,"passed_time":151.4520768,"remaining_time":43.43111027},
{"learn":[0.7050610469],"iteration":544,"passed_time":151.7249048,"remaining_time":43.15111972},
{"learn":[0.7049466797],"iteration":545,"passed_time":152.0014359,"remaining_time":42.87219986},
{"learn":[0.7048009077],"iteration":546,"passed_time":152.2732097,"remaining_time":42.5919581},
{"learn":[0.7046985968],"iteration":547,"passed_time":152.5383999,"remaining_time":42.30992115},
{"learn":[0.7045779697],"iteration":548,"passed_time":152.8005757,"remaining_time":42.02711644},
{"learn":[0.7044828089],"iteration":549,"passed_time":153.0792414,"remaining_time":41.74888403},
{"learn":[0.7043798118],"iteration":550,"passed_time":153.3337388,"remaining_time":41.4641145},
{"learn":[0.7042713303],"iteration":551,"passed_time":153.602779,"remaining_time":41.18335378},
{"learn":[0.7041480738],"iteration":552,"passed_time":153.8784662,"remaining_time":40.90440241},
{"learn":[0.7040145428],"iteration":553,"passed_time":154.1564046,"remaining_time":40.62605609},
{"learn":[0.7039237422],"iteration":554,"passed_time":154.4226221,"remaining_time":40.34464901},
{"learn":[0.7038170533],"iteration":555,"passed_time":154.6978342,"remaining_time":40.06562612},
{"learn":[0.7036659942],"iteration":556,"passed_time":154.9661671,"remaining_time":39.7848508},
{"learn":[0.7035100864],"iteration":557,"passed_time":155.2456837,"remaining_time":39.50696611},
{"learn":[0.7033790634],"iteration":558,"passed_time":155.527539,"remaining_time":39.22966548},
{"learn":[0.7032628057],"iteration":559,"passed_time":155.7967636,"remaining_time":38.94919091},
{"learn":[0.7031483958],"iteration":560,"passed_time":156.0604867,"remaining_time":38.66739332},
{"learn":[0.7030665393],"iteration":561,"passed_time":156.3354286,"remaining_time":38.38841485},
{"learn":[0.7029871921],"iteration":562,"passed_time":156.5959708,"remaining_time":38.10594671},
{"learn":[0.7028519988],"iteration":563,"passed_time":156.8824277,"remaining_time":37.82980527},
{"learn":[0.7026717873],"iteration":564,"passed_time":157.1608037,"remaining_time":37.55169646},
{"learn":[0.7025640391],"iteration":565,"passed_time":157.4308237,"remaining_time":37.27160843},
{"learn":[0.7023924909],"iteration":566,"passed_time":157.7031125,"remaining_time":36.99208811},
{"learn":[0.7022868889],"iteration":567,"passed_time":157.9715834,"remaining_time":36.711706},
{"learn":[0.7021812666],"iteration":568,"passed_time":158.2754612,"remaining_time":36.43951742},
{"learn":[0.7020425831],"iteration":569,"passed_time":158.5495849,"remaining_time":36.16043165},
{"learn":[0.7019289873],"iteration":570,"passed_time":158.837751,"remaining_time":35.88453569},
{"learn":[0.7018298685],"iteration":571,"passed_time":159.1043803,"remaining_time":35.60377741},
{"learn":[0.7017252544],"iteration":572,"passed_time":159.3828987,"remaining_time":35.32570354},
{"learn":[0.7016139206],"iteration":573,"passed_time":159.6476021,"remaining_time":35.04459558},
{"learn":[0.7014648433],"iteration":574,"passed_time":159.9347883,"remaining_time":34.76843224},
{"learn":[0.7012850247],"iteration":575,"passed_time":160.2250561,"remaining_time":34.49289401},
{"learn":[0.7011611762],"iteration":576,"passed_time":160.5042766,"remaining_time":34.21494978},
{"learn":[0.7010763793],"iteration":577,"passed_time":160.764046,"remaining_time":33.93289552},
{"learn":[0.7009751704],"iteration":578,"passed_time":161.040361,"remaining_time":33.65437597},
{"learn":[0.700856053],"iteration":579,"passed_time":161.3202425,"remaining_time":33.37660189},
{"learn":[0.7007631946],"iteration":580,"passed_time":161.5963481,"remaining_time":33.09804719},
{"learn":[0.7006363559],"iteration":581,"passed_time":161.8769705,"remaining_time":32.8204167},
{"learn":[0.7005458123],"iteration":582,"passed_time":162.1477157,"remaining_time":32.54079372},
{"learn":[0.7004752733],"iteration":583,"passed_time":162.415545,"remaining_time":32.26062196},
{"learn":[0.7003633719],"iteration":584,"passed_time":162.6924222,"remaining_time":31.98227102},
{"learn":[0.7002177055],"iteration":585,"passed_time":162.9982522,"remaining_time":31.7095576},
{"learn":[0.7001167678],"iteration":586,"passed_time":163.2778325,"remaining_time":31.43167814},
{"learn":[0.6999938113],"iteration":587,"passed_time":163.5766876,"remaining_time":31.15746431},
{"learn":[0.6998564479],"iteration":588,"passed_time":163.8798578,"remaining_time":30.88398},
{"learn":[0.6997557137],"iteration":589,"passed_time":164.1523263,"remaining_time":30.60467101},
{"learn":[0.6996069702],"iteration":590,"passed_time":164.4410322,"remaining_time":30.32837988},
{"learn":[0.6994796644],"iteration":591,"passed_time":164.7316452,"remaining_time":30.05239473},
{"learn":[0.6993342549],"iteration":592,"passed_time":165.025883,"remaining_time":29.77701431},
{"learn":[0.6992071706],"iteration":593,"passed_time":165.3103678,"remaining_time":29.49982994},
{"learn":[0.6991232001],"iteration":594,"passed_time":165.5761405,"remaining_time":29.21931892},
{"learn":[0.6990038434],"iteration":595,"passed_time":165.8431181,"remaining_time":28.93906759},
{"learn":[0.6989205107],"iteration":596,"passed_time":166.1057287,"remaining_time":28.65810729},
{"learn":[0.6988236238],"iteration":597,"passed_time":166.3827688,"remaining_time":28.3796696},
{"learn":[0.698727356],"iteration":598,"passed_time":166.6385252,"remaining_time":28.09764781},
{"learn":[0.698627696],"iteration":599,"passed_time":166.9069444,"remaining_time":27.81782407},
{"learn":[0.6985016478],"iteration":600,"passed_time":167.1736995,"remaining_time":27.53776415},
{"learn":[0.6983945376],"iteration":601,"passed_time":167.4508068,"remaining_time":27.25943366},
{"learn":[0.698289019],"iteration":602,"passed_time":167.7322011,"remaining_time":26.98179686},
{"learn":[0.6981790644],"iteration":603,"passed_time":168.0172871,"remaining_time":26.70473437},
{"learn":[0.698067959],"iteration":604,"passed_time":168.2983181,"remaining_time":26.42700862},
{"learn":[0.6979703733],"iteration":605,"passed_time":168.571239,"remaining_time":26.14801397},
{"learn":[0.6978558709],"iteration":606,"passed_time":168.8375258,"remaining_time":25.8680229},
{"learn":[0.6977772251],"iteration":607,"passed_time":169.1074505,"remaining_time":25.58862738},
{"learn":[0.6976619466],"iteration":608,"passed_time":169.3836116,"remaining_time":25.31019484},
{"learn":[0.6975368926],"iteration":609,"passed_time":169.6536711,"remaining_time":25.03086951},
{"learn":[0.6974169759],"iteration":610,"passed_time":169.9254439,"remaining_time":24.75182408},
{"learn":[0.6973178599],"iteration":611,"passed_time":170.2033378,"remaining_time":24.47368256},
{"learn":[0.6971888512],"iteration":612,"passed_time":170.4778522,"remaining_time":24.19506222},
{"learn":[0.6970762583],"iteration":613,"passed_time":170.7577713,"remaining_time":23.91721227},
{"learn":[0.696961543],"iteration":614,"passed_time":171.0346756,"remaining_time":23.63893891},
{"learn":[0.696857435],"iteration":615,"passed_time":171.3008746,"remaining_time":23.35921017},
{"learn":[0.6967369289],"iteration":616,"passed_time":171.5790438,"remaining_time":23.08113556},
{"learn":[0.6966614264],"iteration":617,"passed_time":171.8375877,"remaining_time":22.80045662},
{"learn":[0.6965674219],"iteration":618,"passed_time":172.1069499,"remaining_time":22.52126484},
{"learn":[0.6964869437],"iteration":619,"passed_time":172.3729117,"remaining_time":22.24166603},
{"learn":[0.6963475241],"iteration":620,"passed_time":172.6710484,"remaining_time":21.96620422},
{"learn":[0.6962184333],"iteration":621,"passed_time":172.9575761,"remaining_time":21.68921373},
{"learn":[0.696115635],"iteration":622,"passed_time":173.2294081,"remaining_time":21.41037628},
{"learn":[0.696051534],"iteration":623,"passed_time":173.5063122,"remaining_time":21.13217905},
{"learn":[0.6959620531],"iteration":624,"passed_time":173.7772592,"remaining_time":20.85327111},
{"learn":[0.6958574902],"iteration":625,"passed_time":174.0480743,"remaining_time":20.574373},
{"learn":[0.6957475912],"iteration":626,"passed_time":174.3196417,"remaining_time":20.29558826},
{"learn":[0.6955948624],"iteration":627,"passed_time":174.7202723,"remaining_time":20.03162357},
{"learn":[0.6954831147],"iteration":628,"passed_time":174.9858852,"remaining_time":19.75198387},
{"learn":[0.6953355435],"iteration":629,"passed_time":175.2814201,"remaining_time":19.47571335},
{"learn":[0.6952093472],"iteration":630,"passed_time":175.5418892,"remaining_time":19.19554731},
{"learn":[0.6951213561],"iteration":631,"passed_time":175.8084021,"remaining_time":18.91609389},
{"learn":[0.6949877171],"iteration":632,"passed_time":176.084879,"remaining_time":18.63773601},
{"learn":[0.6948303611],"iteration":633,"passed_time":176.38047,"remaining_time":18.36137385},
{"learn":[0.6947450779],"iteration":634,"passed_time":176.6551274,"remaining_time":18.08280831},
{"learn":[0.6946199111],"iteration":635,"passed_time":176.9343547,"remaining_time":17.80471494},
{"learn":[0.694467581],"iteration":636,"passed_time":177.2145608,"remaining_time":17.52671481},
{"learn":[0.694365986],"iteration":637,"passed_time":177.4798282,"remaining_time":17.24725603},
{"learn":[0.6942459313],"iteration":638,"passed_time":177.7573095,"remaining_time":16.96900764},
{"learn":[0.6941721986],"iteration":639,"passed_time":178.0234534,"remaining_time":16.68969876},
{"learn":[0.6940399722],"iteration":640,"passed_time":178.3081085,"remaining_time":16.41213479},
{"learn":[0.6939485683],"iteration":641,"passed_time":178.5737788,"remaining_time":16.1328336},
{"learn":[0.6938464931],"iteration":642,"passed_time":178.8520345,"remaining_time":15.85469046},
{"learn":[0.6937662816],"iteration":643,"passed_time":179.1278537,"remaining_time":15.5763351},
{"learn":[0.693678104],"iteration":644,"passed_time":179.3923482,"remaining_time":15.29702194},
{"learn":[0.6934890217],"iteration":645,"passed_time":179.687235,"remaining_time":15.02029518},
{"learn":[0.6934079168],"iteration":646,"passed_time":179.9781519,"remaining_time":14.7431871},
{"learn":[0.6933305508],"iteration":647,"passed_time":180.2338449,"remaining_time":14.46320978},
{"learn":[0.6931787427],"iteration":648,"passed_time":180.507059,"remaining_time":14.18468415},
{"learn":[0.6930444549],"iteration":649,"passed_time":180.8021841,"remaining_time":13.90786031},
{"learn":[0.6929100903],"iteration":650,"passed_time":181.0810698,"remaining_time":13.62975794},
{"learn":[0.6928124017],"iteration":651,"passed_time":181.3541378,"remaining_time":13.35122487},
{"learn":[0.6927036447],"iteration":652,"passed_time":181.6242931,"remaining_time":13.07249889},
{"learn":[0.6926144316],"iteration":653,"passed_time":181.9145344,"remaining_time":12.7952119},
{"learn":[0.6925164352],"iteration":654,"passed_time":182.1906761,"remaining_time":12.51691668},
{"learn":[0.6924097683],"iteration":655,"passed_time":182.4681517,"remaining_time":12.23871749},
{"learn":[0.6923097406],"iteration":656,"passed_time":182.7351047,"remaining_time":11.95983182},
{"learn":[0.6922129754],"iteration":657,"passed_time":183.0061979,"remaining_time":11.68124667},
{"learn":[0.6921122105],"iteration":658,"passed_time":183.2777349,"remaining_time":11.40271188},
{"learn":[0.6919776574],"iteration":659,"passed_time":183.5629401,"remaining_time":11.12502667},
{"learn":[0.6919011301],"iteration":660,"passed_time":183.8266823,"remaining_time":10.84605236},
{"learn":[0.6918203148],"iteration":661,"passed_time":184.0856272,"remaining_time":10.56684869},
{"learn":[0.6916887678],"iteration":662,"passed_time":184.3639133,"remaining_time":10.28878551},
{"learn":[0.6915573687],"iteration":663,"passed_time":184.6421727,"remaining_time":10.01072021},
{"learn":[0.6914592561],"iteration":664,"passed_time":184.9071727,"remaining_time":9.731956458},
{"learn":[0.6913560466],"iteration":665,"passed_time":185.1896627,"remaining_time":9.454126924},
{"learn":[0.6912509781],"iteration":666,"passed_time":185.451267,"remaining_time":9.17525009},
{"learn":[0.6911440579],"iteration":667,"passed_time":185.7237819,"remaining_time":8.896947637},
{"learn":[0.6910438499],"iteration":668,"passed_time":185.9904777,"remaining_time":8.618392837},
{"learn":[0.6909613119],"iteration":669,"passed_time":186.2579494,"remaining_time":8.339908181},
{"learn":[0.6908135178],"iteration":670,"passed_time":186.5399223,"remaining_time":8.062083081},
{"learn":[0.6907119312],"iteration":671,"passed_time":186.8156174,"remaining_time":7.783984059},
{"learn":[0.6905842679],"iteration":672,"passed_time":187.0808325,"remaining_time":7.505471733},
{"learn":[0.6904668408],"iteration":673,"passed_time":187.3594978,"remaining_time":7.22751772},
{"learn":[0.6903733199],"iteration":674,"passed_time":187.6400995,"remaining_time":6.949633316},
{"learn":[0.6902821402],"iteration":675,"passed_time":187.907447,"remaining_time":6.671270309},
{"learn":[0.6901615221],"iteration":676,"passed_time":188.1881059,"remaining_time":6.393392078},
{"learn":[0.6900078133],"iteration":677,"passed_time":188.4694183,"remaining_time":6.115526848},
{"learn":[0.6899128283],"iteration":678,"passed_time":188.751409,"remaining_time":5.837672442},
{"learn":[0.6897619249],"iteration":679,"passed_time":189.0339287,"remaining_time":5.559821434},
{"learn":[0.6896502921],"iteration":680,"passed_time":189.3013756,"remaining_time":5.281536178},
{"learn":[0.6895693959],"iteration":681,"passed_time":189.5717278,"remaining_time":5.003359385},
{"learn":[0.6894663297],"iteration":682,"passed_time":189.8438364,"remaining_time":4.725249221},
{"learn":[0.6893472341],"iteration":683,"passed_time":190.1284826,"remaining_time":4.447449886},
{"learn":[0.6892202942],"iteration":684,"passed_time":190.4176735,"remaining_time":4.169730076},
{"learn":[0.6891236731],"iteration":685,"passed_time":190.6948119,"remaining_time":3.891730855},
{"learn":[0.689045966],"iteration":686,"passed_time":190.9567392,"remaining_time":3.613446302},
{"learn":[0.6889864761],"iteration":687,"passed_time":191.2287191,"remaining_time":3.335384635},
{"learn":[0.6888579939],"iteration":688,"passed_time":191.5120205,"remaining_time":3.057521373},
{"learn":[0.6887740591],"iteration":689,"passed_time":191.7844482,"remaining_time":2.779484756},
{"learn":[0.6887097661],"iteration":690,"passed_time":192.0466854,"remaining_time":2.501331648},
{"learn":[0.6886403596],"iteration":691,"passed_time":192.3061372,"remaining_time":2.223192338},
{"learn":[0.6885438158],"iteration":692,"passed_time":192.572652,"remaining_time":1.945178303},
{"learn":[0.688444701],"iteration":693,"passed_time":192.8371981,"remaining_time":1.667180387},
{"learn":[0.6883103791],"iteration":694,"passed_time":193.114994,"remaining_time":1.389316503},
{"learn":[0.6881754463],"iteration":695,"passed_time":193.3974225,"remaining_time":1.111479439},
{"learn":[0.6880788853],"iteration":696,"passed_time":193.6753126,"remaining_time":0.8336096667},
{"learn":[0.6880023109],"iteration":697,"passed_time":193.9402173,"remaining_time":0.5557026282},
{"learn":[0.6878865055],"iteration":698,"passed_time":194.2154634,"remaining_time":0.2778475871},
{"learn":[0.6878028093],"iteration":699,"passed_time":194.5050341,"remaining_time":0}
]}